expdata/__init__.py
expdata/explore.py
expdata/onehot.py
expdata-0.0.2.dist-info/LICENSE
expdata-0.0.2.dist-info/METADATA
expdata-0.0.2.dist-info/WHEEL
expdata-0.0.2.dist-info/top_level.txt
expdata-0.0.2.dist-info/RECORD
