Metadata-Version: 2.1
Name: expdata
Version: 0.0.2
Summary: A package that helps data exploration
Home-page: https://github.com/omerfaruksari/expdata
Author: Ömer Faruk Sarı
Author-email: f.omer.sari@outlook.com
License: UNKNOWN
Platform: UNKNOWN
Classifier: Programming Language :: Python :: 3
Classifier: License :: OSI Approved :: MIT License
Classifier: Operating System :: OS Independent
Requires-Python: >=3.6
